propertime/__init__.py
propertime/exceptions.py
propertime/logger.py
propertime/time.py
propertime/utils.py
propertime/tests/__init__.py
propertime/tests/test_time.py
propertime/tests/test_utils.py
propertime-1.0.1.dist-info/LICENSE
propertime-1.0.1.dist-info/METADATA
propertime-1.0.1.dist-info/WHEEL
propertime-1.0.1.dist-info/top_level.txt
propertime-1.0.1.dist-info/RECORD
