Metadata-Version: 2.1
Name: propertime
Version: 1.0.1
Summary: An attempt at proper time management in Python.
Home-page: https://github.com/sarusso/Propertime
Author: Stefano Alberto Russo
Author-email: stefano.russo@gmail.com
License: Apache License 2.0
Platform: UNKNOWN
License-File: LICENSE
Requires-Dist: python-dateutil (<3.0.0,>=2.8.2)
Requires-Dist: pytz
